[
  {
    "id": "poi-uasd",
    "name": "UASD (Universidad Autónoma de Santo Domingo)",
    "category": "universidad",
    "sectorId": "gazcue",
    "icon": "school"
  },
  {
    "id": "poi-unibe",
    "name": "UNIBE (Universidad Iberoamericana)",
    "category": "universidad",
    "sectorId": "gazcue",
    "icon": "school"
  },
  {
    "id": "poi-pucmm",
    "name": "PUCMM (Pontificia Universidad Católica)",
    "category": "universidad",
    "sectorId": "arroyo_hondo",
    "icon": "school"
  },
  {
    "id": "poi-intec",
    "name": "INTEC (Instituto Tecnológico de Santo Domingo)",
    "category": "universidad",
    "sectorId": "los_prados",
    "icon": "school"
  },
  {
    "id": "poi-unphu",
    "name": "UNPHU (Universidad Nacional Pedro Henríquez Ureña)",
    "category": "universidad",
    "sectorId": "los_rios",
    "icon": "school"
  },
  {
    "id": "poi-apec",
    "name": "UNAPEC (Universidad APEC)",
    "category": "universidad",
    "sectorId": "gazcue",
    "icon": "school"
  },
  {
    "id": "poi-utesa",
    "name": "UTESA (Universidad Tecnológica de Santiago)",
    "category": "universidad",
    "sectorId": "herrera",
    "icon": "school"
  },
  {
    "id": "poi-agora",
    "name": "Ágora Mall",
    "category": "plaza",
    "sectorId": "naco",
    "icon": "shopping_bag"
  },
  {
    "id": "poi-acropolis",
    "name": "Acropolis Center",
    "category": "plaza",
    "sectorId": "naco",
    "icon": "shopping_bag"
  },
  {
    "id": "poi-blue-mall",
    "name": "Blue Mall",
    "category": "plaza",
    "sectorId": "piantini",
    "icon": "shopping_bag"
  },
  {
    "id": "poi-sambil",
    "name": "Sambil Santo Domingo",
    "category": "plaza",
    "sectorId": "los_prados",
    "icon": "shopping_bag"
  },
  {
    "id": "poi-megacentro",
    "name": "Megacentro",
    "category": "plaza",
    "sectorId": "los_mina",
    "icon": "shopping_bag"
  },
  {
    "id": "poi-galeria360",
    "name": "Galería 360",
    "category": "plaza",
    "sectorId": "la_julia",
    "icon": "shopping_bag"
  },
  {
    "id": "poi-downtown",
    "name": "Downtown Center",
    "category": "plaza",
    "sectorId": "bella_vista",
    "icon": "shopping_bag"
  },
  {
    "id": "poi-alcazar",
    "name": "Alcázar de Colón",
    "category": "monumento",
    "sectorId": "zona_colonial",
    "icon": "museum"
  },
  {
    "id": "poi-catedral",
    "name": "Catedral Primada de América",
    "category": "monumento",
    "sectorId": "zona_colonial",
    "icon": "church"
  },
  {
    "id": "poi-jardin-botanico",
    "name": "Jardín Botánico Nacional",
    "category": "parque",
    "sectorId": "arroyo_hondo",
    "icon": "park"
  },
  {
    "id": "poi-plaza-cultura",
    "name": "Plaza de la Cultura",
    "category": "monumento",
    "sectorId": "gazcue",
    "icon": "museum"
  },
  {
    "id": "poi-malecon",
    "name": "Malecón de Santo Domingo",
    "category": "atraccion",
    "sectorId": "gazcue",
    "icon": "waves"
  },
  {
    "id": "poi-hospital-dario",
    "name": "Hospital Darío Contreras",
    "category": "hospital",
    "sectorId": "los_mina",
    "icon": "local_hospital"
  },
  {
    "id": "poi-plaza-salud",
    "name": "Hospital General Plaza de la Salud",
    "category": "hospital",
    "sectorId": "los_rios",
    "icon": "local_hospital"
  },
  {
    "id": "poi-cedimat",
    "name": "CEDIMAT",
    "category": "hospital",
    "sectorId": "evaristo_morales",
    "icon": "local_hospital"
  },
  {
    "id": "poi-estadio-quisqueya",
    "name": "Estadio Quisqueya Juan Marichal",
    "category": "deporte",
    "sectorId": "el_millon",
    "icon": "stadium"
  }
]
